pyls_livepy/__init__.py
pyls_livepy/data/noxfile.py
pyls_livepy/plugin.py
pyls_livepy/runner.py
pyls_livepy/tracer.py
pyls_livepy/utils.py
pyls_livepy-0.3.0.dist-info/entry_points.txt
pyls_livepy-0.3.0.dist-info/LICENSE.txt
pyls_livepy-0.3.0.dist-info/WHEEL
pyls_livepy-0.3.0.dist-info/METADATA
pyls_livepy-0.3.0.dist-info/RECORD
