Metadata-Version: 2.1
Name: pyls-livepy
Version: 0.3.0
Summary: A realtime debugging and testing plugin for the Python Language Server.
Home-page: https://gitlab.com/skeledrew/pyls-livepy
License: AGPL-3.0-or-later
Keywords: language-server-protocol,python-lsp-server
Author: Andrew Phillips
Author-email: skeledrew@gmail.com
Requires-Python: >=3.7,<4.0
Classifier: Development Status :: 4 - Beta
Classifier: Intended Audience :: Developers
Classifier: License :: OSI Approved :: GNU Affero General Public License v3 or later (AGPLv3+)
Classifier: Programming Language :: Python :: 3
Classifier: Programming Language :: Python :: 3.7
Classifier: Programming Language :: Python :: 3.8
Classifier: Programming Language :: Python :: 3.9
Classifier: Topic :: Software Development :: Testing :: Unit
Classifier: Topic :: Text Editors :: Integrated Development Environments (IDE)
Classifier: Topic :: Utilities
Provides-Extra: all
Provides-Extra: pyls
Provides-Extra: runs
Requires-Dist: birdseye (>=0.9.1,<0.10.0); extra == "runs" or extra == "all"
Requires-Dist: loguru (>=0.5.3,<0.6.0)
Requires-Dist: python-lsp-server (>=1.1.0,<2.0.0); extra == "pyls" or extra == "all"
Project-URL: Repository, https://gitlab.com/skeledrew/pyls-livepy
